setup.py
runpy2/__init__.py
runpy2/local_pkgutil.py
runpy2/runpy.py
runpy2.egg-info/PKG-INFO
runpy2.egg-info/SOURCES.txt
runpy2.egg-info/dependency_links.txt
runpy2.egg-info/top_level.txt