Metadata-Version: 1.0
Name: runpy2
Version: 2.5
Summary: A package that supports runpy functionality for Python 2.4
Home-page: https://software.sandia.gov/trac/runpy2
Author: William E. Hart
Author-email: wehart@sandia.gov
License: PSF
Keywords: utility
Platform: any
Classifier: Development Status :: 4 - Beta
Classifier: Intended Audience :: End Users/Desktop
Classifier: License :: OSI Approved :: Python Software Foundation License
Classifier: Natural Language :: English
Classifier: Operating System :: Microsoft :: Windows
Classifier: Operating System :: Unix
Classifier: Programming Language :: Python
Classifier: Topic :: Software Development :: Libraries :: Python Modules
